Mattpoltlib/__init__.py
Mattpoltlib/ds.py
Mattpoltlib/dsp.py
Mattpoltlib/ss.py
Mattpoltlib-2.2.dist-info/METADATA
Mattpoltlib-2.2.dist-info/WHEEL
Mattpoltlib-2.2.dist-info/top_level.txt
Mattpoltlib-2.2.dist-info/RECORD
